pypp_bridge_lib_glfw/d_types.py
pypp_bridge_lib_glfw/pypp_data/bridge_jsons/always_pass_by_value.json
pypp_bridge_lib_glfw/pypp_data/bridge_jsons/attr_map.json
pypp_bridge_lib_glfw/pypp_data/bridge_jsons/call_map.json
pypp_bridge_lib_glfw/pypp_data/bridge_jsons/cmake_lists.json
pypp_bridge_lib_glfw/pypp_data/bridge_jsons/import_map.json
pypp_bridge_lib_glfw/pypp_data/bridge_jsons/name_map.json
pypp_bridge_lib_glfw-0.0.0.dist-info/METADATA
pypp_bridge_lib_glfw-0.0.0.dist-info/WHEEL
pypp_bridge_lib_glfw-0.0.0.dist-info/licenses/LICENSE
pypp_bridge_lib_glfw-0.0.0.dist-info/RECORD
