Metadata-Version: 2.4
Name: pypp-bridge-lib-glfw
Version: 0.0.0
Summary: a Py++ bridge-library for glfw
Project-URL: Homepage, https://github.com/curtispuetz/pypp-bridge-lib-glfw
Author-email: Curtis Puetz <pypp.main@gmail.com>
License: MIT
License-File: LICENSE
Requires-Python: >=3.13
Requires-Dist: glfw==2.9.0
